sous_chef/chef.py
sous_chef/app.py
sous_chef/blueprints.py
sous_chef/__init__.py
sous_chef/static/bootstrap-3.1.1.min.js
sous_chef/static/jquery-1.11.0.min.js
sous_chef/static/bootstrap-3.1.1.min.css
sous_chef/static/sous-chef.css
sous_chef/static/bootstrap-theme-3.1.1.min.css
sous_chef/templates/macros.html
sous_chef/templates/404.html
sous_chef/templates/base.html
sous_chef/templates/nodes/index.html
sous_chef/templates/nodes/macros.html
sous_chef/templates/nodes/view.html
sous_chef/templates/packages/index_for_type.html
sous_chef/templates/packages/macros.html
sous_chef/templates/packages/index_by_type.html
sous_chef/templates/packages/view.html
sous_chef/templates/environments/index.html
sous_chef/templates/environments/view.html
sous_chef/templates/roles/index.html
sous_chef/templates/roles/view.html
sous_chef-2.7.0.dist-info/WHEEL
sous_chef-2.7.0.dist-info/RECORD
sous_chef-2.7.0.dist-info/DESCRIPTION.rst
sous_chef-2.7.0.dist-info/metadata.json
sous_chef-2.7.0.dist-info/top_level.txt
sous_chef-2.7.0.dist-info/METADATA
