Metadata-Version: 2.0
Name: sous-chef
Version: 2.7.0
Summary: A web frontend for the Chef server index
Home-page: https://github.com/datasift/sous-chef
Author: Sam Clements
Author-email: sam.clements@datasift.com
License: MIT
Platform: UNKNOWN
Classifier: Development Status :: 3 - Alpha
Classifier: Programming Language :: Python
Classifier: Programming Language :: Python :: 2
Classifier: Programming Language :: Python :: 2.6
Classifier: Programming Language :: Python :: 2.7
Requires-Dist: flask (>=0.10.0)
Requires-Dist: pychef (>=0.2.3)
Provides-Extra: debug
Requires-Dist: flask-debugtoolbar (>=0.9.0); extra == 'debug'
Provides-Extra: deploy
Requires-Dist: gunicorn (>=18.0); extra == 'deploy'
